README.md
setup.py
colubrid_helpers/__init__.py
colubrid_helpers/__main__.py
colubrid_helpers/routestructure.py
colubrid_helpers/template.py
colubrid_helpers.egg-info/PKG-INFO
colubrid_helpers.egg-info/SOURCES.txt
colubrid_helpers.egg-info/dependency_links.txt
colubrid_helpers.egg-info/entry_points.txt
colubrid_helpers.egg-info/top_level.txt