Metadata-Version: 1.1
Name: colubrid-helpers
Version: 1.0.39
Summary: Colubrid libraries
Home-page: https://github.com/rhonalejandro/Colubrid-Framework
Author: Rhonald Alejandro Brito Querales
Author-email: rhonalejandro@gmail.com
License: MIT
Keywords: colubrid-helpers
Platform: UNKNOWN
Classifier: Development Status :: 4 - Beta
Classifier: Intended Audience :: Developers
Classifier: Topic :: Internet
Classifier: License :: OSI Approved :: MIT License
Classifier: Programming Language :: Python :: 3.7
Classifier: Programming Language :: Python :: 3.10
